elmada/__init__.py
elmada/cc_share.py
elmada/eu_pwl.py
elmada/exceptions.py
elmada/from_entsoe.py
elmada/from_geo_scraped.py
elmada/from_geo_via_morph.py
elmada/from_opsd.py
elmada/from_other.py
elmada/from_smard.py
elmada/helper.py
elmada/main.py
elmada/mappings.py
elmada/mode.py
elmada/paths.py
elmada/plots.py
elmada/data/raw/destatis/energiepreisentwicklung-xlsx-5619001.xls
elmada/data/raw/sandbag/eua-price.csv
elmada/data/raw/smard/Day-ahead_prices_2015.csv
elmada/data/raw/smard/Day-ahead_prices_2018.csv
elmada/data/raw/smard/readme.txt
elmada/data/raw/tranberg/specific_emission_factors.csv
elmada/data/raw/worldbank/readme.txt
elmada/data/raw/worldbank/Data_Extract_From_World_Development_Indicators/Data.csv
elmada/data/raw/worldbank/Data_Extract_From_World_Development_Indicators/Metadata.csv
elmada/data/safe_cache/2017_AT_gen_entsoe.parquet
elmada/data/safe_cache/2017_AT_installedGen_entsoe.parquet
elmada/data/safe_cache/2017_BE_gen_entsoe.parquet
elmada/data/safe_cache/2017_BE_installedGen_entsoe.parquet
elmada/data/safe_cache/2017_BG_gen_entsoe.parquet
elmada/data/safe_cache/2017_CH_gen_entsoe.parquet
elmada/data/safe_cache/2017_CZ_gen_entsoe.parquet
elmada/data/safe_cache/2017_CZ_installedGen_entsoe.parquet
elmada/data/safe_cache/2017_DE_gen_entsoe.parquet
elmada/data/safe_cache/2017_DE_installedGen_entsoe.parquet
elmada/data/safe_cache/2017_DK_gen_entsoe.parquet
elmada/data/safe_cache/2017_DK_installedGen_entsoe.parquet
elmada/data/safe_cache/2017_EE_gen_entsoe.parquet
elmada/data/safe_cache/2017_ES_gen_entsoe.parquet
elmada/data/safe_cache/2017_ES_installedGen_entsoe.parquet
elmada/data/safe_cache/2017_FI_gen_entsoe.parquet
elmada/data/safe_cache/2017_FI_installedGen_entsoe.parquet
elmada/data/safe_cache/2017_FR_gen_entsoe.parquet
elmada/data/safe_cache/2017_FR_installedGen_entsoe.parquet
elmada/data/safe_cache/2017_GB_gen_entsoe.parquet
elmada/data/safe_cache/2017_GB_installedGen_entsoe.parquet
elmada/data/safe_cache/2017_GR_gen_entsoe.parquet
elmada-0.1.0.dist-info/LICENSE.md
elmada-0.1.0.dist-info/METADATA
elmada-0.1.0.dist-info/WHEEL
elmada-0.1.0.dist-info/top_level.txt
elmada-0.1.0.dist-info/RECORD
