Metadata-Version: 2.1
Name: elmada
Version: 0.1.0
Summary: Dynamic electricity carbon emission factors and prices for Europe
Home-page: https://github.com/DrafProject/elmada
Author: Markus Fleschutz
Author-email: mfleschutz@gmail.com
License: LGPLv3
Keywords: energy market data,energy systems,carbon emission factors,demand response
Platform: UNKNOWN
Classifier: Development Status :: 4 - Beta
Classifier: Intended Audience :: Developers
Classifier: Intended Audience :: Science/Research
Classifier: License :: OSI Approved :: GNU Lesser General Public License v3 (LGPLv3)
Classifier: Natural Language :: English
Classifier: Operating System :: OS Independent
Classifier: Programming Language :: Python :: 3 :: Only
Classifier: Programming Language :: Python :: 3
Classifier: Topic :: Scientific/Engineering :: Information Analysis
Classifier: Topic :: Scientific/Engineering
Classifier: Topic :: Software Development :: Libraries :: Python Modules
Requires-Python: >=3.7
License-File: LICENSE.md
Requires-Dist: appdirs
Requires-Dist: beautifulsoup4
Requires-Dist: entsoe-py (==0.2.10)
Requires-Dist: ipython
Requires-Dist: lxml
Requires-Dist: matplotlib
Requires-Dist: numpy
Requires-Dist: pandas
Requires-Dist: pyarrow
Requires-Dist: quandl
Requires-Dist: requests
Requires-Dist: scipy
Requires-Dist: xlrd
Provides-Extra: dev
Requires-Dist: black ; extra == 'dev'
Requires-Dist: iso3166 ; extra == 'dev'
Requires-Dist: isort ; extra == 'dev'
Requires-Dist: mypy ; extra == 'dev'
Requires-Dist: plotly ; extra == 'dev'
Requires-Dist: pytest-cov ; extra == 'dev'
Requires-Dist: pytest-mock ; extra == 'dev'
Requires-Dist: pytest-responsemock ; extra == 'dev'
Requires-Dist: pytest ; extra == 'dev'
